vexy_formi/__init__.py
vexy_formi/cli.py
vexy_formi/config.py
vexy_formi/core.py
vexy_formi/files.py
vexy_formi/performance.py
vexy_formi/safety.py
vexy_formi/tools.py
vexy_formi/tools_install.py
vexy_formi/tools_update.py
vexy_formi-1.0.4.dist-info/METADATA
vexy_formi-1.0.4.dist-info/WHEEL
vexy_formi-1.0.4.dist-info/entry_points.txt
vexy_formi-1.0.4.dist-info/licenses/LICENSE
vexy_formi-1.0.4.dist-info/RECORD
